httpx_secure/__init__.py
httpx_secure/py.typed
httpx_secure-1.1.0.dist-info/METADATA
httpx_secure-1.1.0.dist-info/WHEEL
httpx_secure-1.1.0.dist-info/licenses/LICENSE
httpx_secure-1.1.0.dist-info/RECORD
