Metadata-Version: 2.4
Name: httpx-secure
Version: 1.1.0
Summary: Drop-in SSRF protection for httpx
Project-URL: Repository, https://github.com/Zaczero/httpx-secure
Project-URL: Issues, https://github.com/Zaczero/httpx-secure/issues
Author-email: Kamil Monicz <kamil@monicz.dev>
License-Expression: 0BSD
License-File: LICENSE
Keywords: anyio,async,asyncio,client,dns,dns-cache,http,httpx,security,ssrf,ssrf-protection,trio,web-security
Classifier: Development Status :: 5 - Production/Stable
Classifier: Framework :: AnyIO
Classifier: Framework :: AsyncIO
Classifier: Framework :: Trio
Classifier: Intended Audience :: Developers
Classifier: License :: OSI Approved :: Zero-Clause BSD (0BSD)
Classifier: Operating System :: OS Independent
Classifier: Programming Language :: Python :: 3
Classifier: Programming Language :: Python :: 3.9
Classifier: Programming Language :: Python :: 3.10
Classifier: Programming Language :: Python :: 3.11
Classifier: Programming Language :: Python :: 3.12
Classifier: Programming Language :: Python :: 3.13
Classifier: Programming Language :: Python :: 3.14
Classifier: Topic :: Internet :: WWW/HTTP
Classifier: Topic :: Internet :: WWW/HTTP :: Dynamic Content
Classifier: Topic :: Security
Classifier: Topic :: Software Development :: Libraries :: Python Modules
Classifier: Topic :: System :: Networking
Classifier: Typing :: Typed
Requires-Python: >=3.9
Requires-Dist: anyio
Requires-Dist: httpx
